{
  "updateTime": "2026-02-05T20:38:22.548Z",
  "updateTimeLocal": "2026/2/6 上午4:38:22",
  "currency": "TWD",
  "cryptos": [
    {
      "id": "bitcoin",
      "symbol": "BTC",
      "name": "Bitcoin",
      "icon": "₿",
      "price": 2012591,
      "priceUsd": 63891.77777777778,
      "change24h": -13.29126,
      "marketCap": 40286205733421,
      "volume24h": 3903452167824,
      "high24h": 2326018,
      "low24h": 2016835
    },
    {
      "id": "ethereum",
      "symbol": "ETH",
      "name": "Ethereum",
      "icon": "Ξ",
      "price": 58914,
      "priceUsd": 1870.2857142857142,
      "change24h": -14.20224,
      "marketCap": 7111506379216,
      "volume24h": 1831751404024,
      "high24h": 68666,
      "low24h": 59110
    },
    {
      "id": "binancecoin",
      "symbol": "BNB",
      "name": "BNB",
      "icon": "🔶",
      "price": 19780.64,
      "priceUsd": 627.9568253968254,
      "change24h": -12.39917,
      "marketCap": 2695428738675,
      "volume24h": 117420568535,
      "high24h": 22580,
      "low24h": 19740.58
    },
    {
      "id": "ripple",
      "symbol": "XRP",
      "name": "XRP",
      "icon": "✕",
      "price": 36.97,
      "priceUsd": 1.1736507936507936,
      "change24h": -23.92775,
      "marketCap": 2251950367063,
      "volume24h": 310405871339,
      "high24h": 48.64,
      "low24h": 36.78
    },
    {
      "id": "solana",
      "symbol": "SOL",
      "name": "Solana",
      "icon": "◎",
      "price": 2489.88,
      "priceUsd": 79.04380952380953,
      "change24h": -15.61804,
      "marketCap": 1413681183168,
      "volume24h": 323641791733,
      "high24h": 2950.72,
      "low24h": 2496.12
    },
    {
      "id": "dogecoin",
      "symbol": "DOGE",
      "name": "Dogecoin",
      "icon": "🐕",
      "price": 2.82,
      "priceUsd": 0.08952380952380952,
      "change24h": -14.72654,
      "marketCap": 475411671364,
      "volume24h": 93231177672,
      "high24h": 3.31,
      "low24h": 2.82
    },
    {
      "id": "cardano",
      "symbol": "ADA",
      "name": "Cardano",
      "icon": "₳",
      "price": 7.87,
      "priceUsd": 0.24984126984126984,
      "change24h": -14.16913,
      "marketCap": 288930190181,
      "volume24h": 39149636075,
      "high24h": 9.17,
      "low24h": 7.84
    },
    {
      "id": "chainlink",
      "symbol": "LINK",
      "name": "Chainlink",
      "icon": "⬡",
      "price": 253.59,
      "priceUsd": 8.050476190476191,
      "change24h": -14.32438,
      "marketCap": 179673022005,
      "volume24h": 29888782203,
      "high24h": 296.14,
      "low24h": 253.72
    },
    {
      "id": "avalanche-2",
      "symbol": "AVAX",
      "name": "Avalanche",
      "icon": "🔺",
      "price": 266.2,
      "priceUsd": 8.450793650793651,
      "change24h": -14.51816,
      "marketCap": 114983642884,
      "volume24h": 23668681359,
      "high24h": 311.41,
      "low24h": 266.25
    },
    {
      "id": "polkadot",
      "symbol": "DOT",
      "name": "Polkadot",
      "icon": "●",
      "price": 39.66,
      "priceUsd": 1.259047619047619,
      "change24h": -15.04692,
      "marketCap": 65877348683,
      "volume24h": 8257712705,
      "high24h": 46.69,
      "low24h": 39.63
    }
  ]
}