{
  "updateTime": "2026-01-21T13:52:05.025Z",
  "updateTimeLocal": "2026/1/21 下午9:52:05",
  "currency": "TWD",
  "cryptos": [
    {
      "id": "bitcoin",
      "symbol": "BTC",
      "name": "Bitcoin",
      "icon": "₿",
      "price": 2796687,
      "priceUsd": 88783.71428571429,
      "change24h": -2.76635,
      "marketCap": 55956590798722,
      "volume24h": 1865243696446,
      "high24h": 2886577,
      "low24h": 2788062
    },
    {
      "id": "ethereum",
      "symbol": "ETH",
      "name": "Ethereum",
      "icon": "Ξ",
      "price": 92268,
      "priceUsd": 2929.1428571428573,
      "change24h": -5.32199,
      "marketCap": 11153496714631,
      "volume24h": 1000759016539,
      "high24h": 97593,
      "low24h": 91756
    },
    {
      "id": "binancecoin",
      "symbol": "BNB",
      "name": "BNB",
      "icon": "🔶",
      "price": 27533,
      "priceUsd": 874.063492063492,
      "change24h": -3.94093,
      "marketCap": 3755073887823,
      "volume24h": 97479140776,
      "high24h": 28782,
      "low24h": 27322
    },
    {
      "id": "ripple",
      "symbol": "XRP",
      "name": "XRP",
      "icon": "✕",
      "price": 59.78,
      "priceUsd": 1.8977777777777778,
      "change24h": -1.52437,
      "marketCap": 3639652864318,
      "volume24h": 113114783508,
      "high24h": 61.05,
      "low24h": 59.47
    },
    {
      "id": "solana",
      "symbol": "SOL",
      "name": "Solana",
      "icon": "◎",
      "price": 4009.73,
      "priceUsd": 127.29301587301588,
      "change24h": -1.42162,
      "marketCap": 2268380150779,
      "volume24h": 160136467717,
      "high24h": 4083.29,
      "low24h": 3986.86
    },
    {
      "id": "dogecoin",
      "symbol": "DOGE",
      "name": "Dogecoin",
      "icon": "🐕",
      "price": 3.87,
      "priceUsd": 0.12285714285714286,
      "change24h": -2.10831,
      "marketCap": 653188580934,
      "volume24h": 40044352767,
      "high24h": 4,
      "low24h": 3.85
    },
    {
      "id": "cardano",
      "symbol": "ADA",
      "name": "Cardano",
      "icon": "₳",
      "price": 11.14,
      "priceUsd": 0.35365079365079366,
      "change24h": -1.75864,
      "marketCap": 410288846704,
      "volume24h": 18655931643,
      "high24h": 11.43,
      "low24h": 11.08
    },
    {
      "id": "chainlink",
      "symbol": "LINK",
      "name": "Chainlink",
      "icon": "⬡",
      "price": 383.07,
      "priceUsd": 12.16095238095238,
      "change24h": -2.89962,
      "marketCap": 271521869976,
      "volume24h": 13967268548,
      "high24h": 397.28,
      "low24h": 381.51
    },
    {
      "id": "avalanche-2",
      "symbol": "AVAX",
      "name": "Avalanche",
      "icon": "🔺",
      "price": 379.85,
      "priceUsd": 12.05873015873016,
      "change24h": -2.94128,
      "marketCap": 163791377482,
      "volume24h": 10998892083,
      "high24h": 394.85,
      "low24h": 378.61
    },
    {
      "id": "polkadot",
      "symbol": "DOT",
      "name": "Polkadot",
      "icon": "●",
      "price": 60.3,
      "priceUsd": 1.9142857142857141,
      "change24h": -2.20821,
      "marketCap": 99955745383,
      "volume24h": 4120482390,
      "high24h": 62.13,
      "low24h": 60.03
    }
  ]
}