{
  "updateTime": "2026-01-30T20:35:22.286Z",
  "updateTimeLocal": "2026/1/31 上午4:35:22",
  "currency": "TWD",
  "cryptos": [
    {
      "id": "bitcoin",
      "symbol": "BTC",
      "name": "Bitcoin",
      "icon": "₿",
      "price": 2653292,
      "priceUsd": 84231.49206349206,
      "change24h": 0.81213,
      "marketCap": 52936292271401,
      "volume24h": 2542565526232,
      "high24h": 2663150,
      "low24h": 2554775
    },
    {
      "id": "ethereum",
      "symbol": "ETH",
      "name": "Ethereum",
      "icon": "Ξ",
      "price": 84766,
      "priceUsd": 2690.9841269841268,
      "change24h": -3.24704,
      "marketCap": 10229653212296,
      "volume24h": 1339979042694,
      "high24h": 88585,
      "low24h": 83367
    },
    {
      "id": "binancecoin",
      "symbol": "BNB",
      "name": "BNB",
      "icon": "🔶",
      "price": 26839,
      "priceUsd": 852.031746031746,
      "change24h": -0.5153,
      "marketCap": 3659711100657,
      "volume24h": 84557040569,
      "high24h": 27243,
      "low24h": 26216
    },
    {
      "id": "ripple",
      "symbol": "XRP",
      "name": "XRP",
      "icon": "✕",
      "price": 55.3,
      "priceUsd": 1.7555555555555555,
      "change24h": -1.50468,
      "marketCap": 3365893859877,
      "volume24h": 153961469108,
      "high24h": 56.75,
      "low24h": 54.37
    },
    {
      "id": "solana",
      "symbol": "SOL",
      "name": "Solana",
      "icon": "◎",
      "price": 3709.6,
      "priceUsd": 117.76507936507936,
      "change24h": 1.1448,
      "marketCap": 2100709764544,
      "volume24h": 233890354476,
      "high24h": 3741.06,
      "low24h": 3554.17
    },
    {
      "id": "dogecoin",
      "symbol": "DOGE",
      "name": "Dogecoin",
      "icon": "🐕",
      "price": 3.68,
      "priceUsd": 0.11682539682539683,
      "change24h": 1.4326,
      "marketCap": 620254160855,
      "volume24h": 53490715382,
      "high24h": 3.73,
      "low24h": 3.54
    },
    {
      "id": "cardano",
      "symbol": "ADA",
      "name": "Cardano",
      "icon": "₳",
      "price": 10.3,
      "priceUsd": 0.326984126984127,
      "change24h": -0.94064,
      "marketCap": 378842838575,
      "volume24h": 23300917330,
      "high24h": 10.52,
      "low24h": 10.06
    },
    {
      "id": "chainlink",
      "symbol": "LINK",
      "name": "Chainlink",
      "icon": "⬡",
      "price": 340.85,
      "priceUsd": 10.820634920634921,
      "change24h": -1.03707,
      "marketCap": 241320254977,
      "volume24h": 19277019129,
      "high24h": 349.31,
      "low24h": 333.83
    },
    {
      "id": "avalanche-2",
      "symbol": "AVAX",
      "name": "Avalanche",
      "icon": "🔺",
      "price": 344.34,
      "priceUsd": 10.93142857142857,
      "change24h": -0.11465,
      "marketCap": 148559043940,
      "volume24h": 15508168424,
      "high24h": 347.41,
      "low24h": 338.66
    },
    {
      "id": "polkadot",
      "symbol": "DOT",
      "name": "Polkadot",
      "icon": "●",
      "price": 53.62,
      "priceUsd": 1.702222222222222,
      "change24h": -1.07305,
      "marketCap": 89027452113,
      "volume24h": 5834348949,
      "high24h": 54.74,
      "low24h": 52.51
    }
  ]
}