{
  "updateTime": "2025-12-25T07:25:08.062Z",
  "updateTimeLocal": "2025/12/25 下午3:25:08",
  "currency": "TWD",
  "cryptos": [
    {
      "id": "bitcoin",
      "symbol": "BTC",
      "name": "Bitcoin",
      "icon": "₿",
      "price": 2758681,
      "priceUsd": 87577.1746031746,
      "change24h": 0.92746,
      "marketCap": 55090829750466,
      "volume24h": 778951078654,
      "high24h": 2765285,
      "low24h": 2721106
    },
    {
      "id": "ethereum",
      "symbol": "ETH",
      "name": "Ethereum",
      "icon": "Ξ",
      "price": 92399,
      "priceUsd": 2933.3015873015875,
      "change24h": 0.23729,
      "marketCap": 11160231638536,
      "volume24h": 357670226734,
      "high24h": 93019,
      "low24h": 91336
    },
    {
      "id": "binancecoin",
      "symbol": "BNB",
      "name": "BNB",
      "icon": "🔶",
      "price": 26480,
      "priceUsd": 840.6349206349206,
      "change24h": 0.40436,
      "marketCap": 3647510412935,
      "volume24h": 23096295068,
      "high24h": 26709,
      "low24h": 26205
    },
    {
      "id": "ripple",
      "symbol": "XRP",
      "name": "XRP",
      "icon": "✕",
      "price": 58.89,
      "priceUsd": 1.8695238095238096,
      "change24h": 1.192,
      "marketCap": 3567085477860,
      "volume24h": 48418758507,
      "high24h": 58.95,
      "low24h": 58.19
    },
    {
      "id": "solana",
      "symbol": "SOL",
      "name": "Solana",
      "icon": "◎",
      "price": 3838.74,
      "priceUsd": 121.86476190476189,
      "change24h": 0.51752,
      "marketCap": 2162597447615,
      "volume24h": 68205752442,
      "high24h": 3873.87,
      "low24h": 3808.54
    },
    {
      "id": "dogecoin",
      "symbol": "DOGE",
      "name": "Dogecoin",
      "icon": "🐕",
      "price": 4.02,
      "priceUsd": 0.1276190476190476,
      "change24h": 0.50369,
      "marketCap": 676697125625,
      "volume24h": 17489654236,
      "high24h": 4.06,
      "low24h": 3.98
    },
    {
      "id": "cardano",
      "symbol": "ADA",
      "name": "Cardano",
      "icon": "₳",
      "price": 11.29,
      "priceUsd": 0.3584126984126984,
      "change24h": 0.70361,
      "marketCap": 413909296781,
      "volume24h": 11167722621,
      "high24h": 11.35,
      "low24h": 11.11
    },
    {
      "id": "chainlink",
      "symbol": "LINK",
      "name": "Chainlink",
      "icon": "⬡",
      "price": 386.34,
      "priceUsd": 12.264761904761905,
      "change24h": 0.89269,
      "marketCap": 273614817272,
      "volume24h": 8642161609,
      "high24h": 388.44,
      "low24h": 379.58
    },
    {
      "id": "avalanche-2",
      "symbol": "AVAX",
      "name": "Avalanche",
      "icon": "🔺",
      "price": 383.16,
      "priceUsd": 12.163809523809524,
      "change24h": 1.73529,
      "marketCap": 164636581214,
      "volume24h": 6896423053,
      "high24h": 383.56,
      "low24h": 374.66
    },
    {
      "id": "polkadot",
      "symbol": "DOT",
      "name": "Polkadot",
      "icon": "●",
      "price": 54.61,
      "priceUsd": 1.7336507936507937,
      "change24h": 0.57585,
      "marketCap": 90145502985,
      "volume24h": 2936512447,
      "high24h": 55.03,
      "low24h": 53.98
    }
  ]
}