{
  "updateTime": "2025-12-29T10:28:08.947Z",
  "updateTimeLocal": "2025/12/29 下午6:28:08",
  "currency": "TWD",
  "cryptos": [
    {
      "id": "bitcoin",
      "symbol": "BTC",
      "name": "Bitcoin",
      "icon": "₿",
      "price": 2756142,
      "priceUsd": 87496.57142857143,
      "change24h": -0.10236,
      "marketCap": 55032669748787,
      "volume24h": 1254678519453,
      "high24h": 2831880,
      "low24h": 2744512
    },
    {
      "id": "ethereum",
      "symbol": "ETH",
      "name": "Ethereum",
      "icon": "Ξ",
      "price": 93124,
      "priceUsd": 2956.3174603174602,
      "change24h": 0.91151,
      "marketCap": 11238405548148,
      "volume24h": 659694510840,
      "high24h": 95753,
      "low24h": 91893
    },
    {
      "id": "binancecoin",
      "symbol": "BNB",
      "name": "BNB",
      "icon": "🔶",
      "price": 26728,
      "priceUsd": 848.5079365079365,
      "change24h": 0.36029,
      "marketCap": 3681057806887,
      "volume24h": 52482878992,
      "high24h": 27319,
      "low24h": 26598
    },
    {
      "id": "ripple",
      "symbol": "XRP",
      "name": "XRP",
      "icon": "✕",
      "price": 58.84,
      "priceUsd": 1.867936507936508,
      "change24h": 0.36821,
      "marketCap": 3563957377140,
      "volume24h": 52248866316,
      "high24h": 60.07,
      "low24h": 58.2
    },
    {
      "id": "solana",
      "symbol": "SOL",
      "name": "Solana",
      "icon": "◎",
      "price": 3943.77,
      "priceUsd": 125.19904761904762,
      "change24h": 0.99532,
      "marketCap": 2219507135781,
      "volume24h": 141512344195,
      "high24h": 4055.46,
      "low24h": 3864.91
    },
    {
      "id": "dogecoin",
      "symbol": "DOGE",
      "name": "Dogecoin",
      "icon": "🐕",
      "price": 3.93,
      "priceUsd": 0.12476190476190477,
      "change24h": 1.01748,
      "marketCap": 661039603320,
      "volume24h": 25183660460,
      "high24h": 4.01,
      "low24h": 3.86
    },
    {
      "id": "cardano",
      "symbol": "ADA",
      "name": "Cardano",
      "icon": "₳",
      "price": 11.61,
      "priceUsd": 0.36857142857142855,
      "change24h": -0.31902,
      "marketCap": 425540836595,
      "volume24h": 20310515361,
      "high24h": 12,
      "low24h": 11.37
    },
    {
      "id": "chainlink",
      "symbol": "LINK",
      "name": "Chainlink",
      "icon": "⬡",
      "price": 393.54,
      "priceUsd": 12.493333333333334,
      "change24h": 0.79002,
      "marketCap": 278646044379,
      "volume24h": 12507564247,
      "high24h": 407,
      "low24h": 387.13
    },
    {
      "id": "avalanche-2",
      "symbol": "AVAX",
      "name": "Avalanche",
      "icon": "🔺",
      "price": 399.19,
      "priceUsd": 12.672698412698413,
      "change24h": -0.32158,
      "marketCap": 171473799410,
      "volume24h": 10159741223,
      "high24h": 411.78,
      "low24h": 393.4
    },
    {
      "id": "polkadot",
      "symbol": "DOT",
      "name": "Polkadot",
      "icon": "●",
      "price": 58.28,
      "priceUsd": 1.8501587301587301,
      "change24h": -1.76561,
      "marketCap": 96144869328,
      "volume24h": 4209773003,
      "high24h": 59.6,
      "low24h": 57.59
    }
  ]
}