{
  "updateTime": "2025-12-18T03:23:57.302Z",
  "updateTimeLocal": "2025/12/18 上午11:23:57",
  "currency": "TWD",
  "cryptos": [
    {
      "id": "bitcoin",
      "symbol": "BTC",
      "name": "Bitcoin",
      "icon": "₿",
      "price": 2725872,
      "priceUsd": 86535.61904761905,
      "change24h": -1.17726,
      "marketCap": 54536942206399,
      "volume24h": 1582330575645,
      "high24h": 2837655,
      "low24h": 2689949
    },
    {
      "id": "ethereum",
      "symbol": "ETH",
      "name": "Ethereum",
      "icon": "Ξ",
      "price": 89222,
      "priceUsd": 2832.4444444444443,
      "change24h": -4.29605,
      "marketCap": 10769709458859,
      "volume24h": 851712125272,
      "high24h": 95105,
      "low24h": 88104
    },
    {
      "id": "binancecoin",
      "symbol": "BNB",
      "name": "BNB",
      "icon": "🔶",
      "price": 26545,
      "priceUsd": 842.6984126984127,
      "change24h": -2.88872,
      "marketCap": 3656297425864,
      "volume24h": 79196450491,
      "high24h": 27492,
      "low24h": 26287
    },
    {
      "id": "ripple",
      "symbol": "XRP",
      "name": "XRP",
      "icon": "✕",
      "price": 58.52,
      "priceUsd": 1.857777777777778,
      "change24h": -3.87259,
      "marketCap": 3553172271762,
      "volume24h": 105935253939,
      "high24h": 62.36,
      "low24h": 58.31
    },
    {
      "id": "solana",
      "symbol": "SOL",
      "name": "Solana",
      "icon": "◎",
      "price": 3891.28,
      "priceUsd": 123.53269841269842,
      "change24h": -4.49832,
      "marketCap": 2194074704391,
      "volume24h": 189667118244,
      "high24h": 4196.74,
      "low24h": 3835.18
    },
    {
      "id": "dogecoin",
      "symbol": "DOGE",
      "name": "Dogecoin",
      "icon": "🐕",
      "price": 3.96,
      "priceUsd": 0.12571428571428572,
      "change24h": -4.48528,
      "marketCap": 605594938576,
      "volume24h": 43495352897,
      "high24h": 4.27,
      "low24h": 3.94
    },
    {
      "id": "cardano",
      "symbol": "ADA",
      "name": "Cardano",
      "icon": "₳",
      "price": 11.52,
      "priceUsd": 0.3657142857142857,
      "change24h": -5.09326,
      "marketCap": 422345553196,
      "volume24h": 21279191443,
      "high24h": 12.53,
      "low24h": 11.5
    },
    {
      "id": "chainlink",
      "symbol": "LINK",
      "name": "Chainlink",
      "icon": "⬡",
      "price": 384.56,
      "priceUsd": 12.208253968253969,
      "change24h": -5.35737,
      "marketCap": 267984496256,
      "volume24h": 21191906886,
      "high24h": 411.79,
      "low24h": 383.12
    },
    {
      "id": "avalanche-2",
      "symbol": "AVAX",
      "name": "Avalanche",
      "icon": "🔺",
      "price": 370.47,
      "priceUsd": 11.760952380952382,
      "change24h": -4.76936,
      "marketCap": 159686777874,
      "volume24h": 13237949561,
      "high24h": 395.03,
      "low24h": 369.88
    },
    {
      "id": "polkadot",
      "symbol": "DOT",
      "name": "Polkadot",
      "icon": "●",
      "price": 56.69,
      "priceUsd": 1.7996825396825396,
      "change24h": -5.28928,
      "marketCap": 93519305159,
      "volume24h": 6868434666,
      "high24h": 61.16,
      "low24h": 56.62
    }
  ]
}