{
  "updateTime": "2026-01-13T14:29:35.355Z",
  "updateTimeLocal": "2026/1/13 下午10:29:35",
  "currency": "TWD",
  "cryptos": [
    {
      "id": "bitcoin",
      "symbol": "BTC",
      "name": "Bitcoin",
      "icon": "₿",
      "price": 2910841,
      "priceUsd": 92407.6507936508,
      "change24h": 2.1306,
      "marketCap": 58107558190158,
      "volume24h": 1505787393342,
      "high24h": 2920195,
      "low24h": 2850117
    },
    {
      "id": "ethereum",
      "symbol": "ETH",
      "name": "Ethereum",
      "icon": "Ξ",
      "price": 99397,
      "priceUsd": 3155.4603174603176,
      "change24h": 2.35036,
      "marketCap": 11987418989873,
      "volume24h": 764979004826,
      "high24h": 99371,
      "low24h": 97115
    },
    {
      "id": "ripple",
      "symbol": "XRP",
      "name": "XRP",
      "icon": "✕",
      "price": 65.64,
      "priceUsd": 2.083809523809524,
      "change24h": 1.42469,
      "marketCap": 3982669010218,
      "volume24h": 94456863172,
      "high24h": 66.31,
      "low24h": 64.51
    },
    {
      "id": "binancecoin",
      "symbol": "BNB",
      "name": "BNB",
      "icon": "🔶",
      "price": 28727,
      "priceUsd": 911.968253968254,
      "change24h": 1.55595,
      "marketCap": 3953525925652,
      "volume24h": 62553285324,
      "high24h": 28881,
      "low24h": 28287
    },
    {
      "id": "solana",
      "symbol": "SOL",
      "name": "Solana",
      "icon": "◎",
      "price": 4505.74,
      "priceUsd": 143.03936507936507,
      "change24h": 2.39557,
      "marketCap": 2545056761475,
      "volume24h": 224104487399,
      "high24h": 4535.27,
      "low24h": 4366.46
    },
    {
      "id": "dogecoin",
      "symbol": "DOGE",
      "name": "Dogecoin",
      "icon": "🐕",
      "price": 4.43,
      "priceUsd": 0.1406349206349206,
      "change24h": 3.24821,
      "marketCap": 744537385080,
      "volume24h": 36988693068,
      "high24h": 4.42,
      "low24h": 4.29
    },
    {
      "id": "cardano",
      "symbol": "ADA",
      "name": "Cardano",
      "icon": "₳",
      "price": 12.55,
      "priceUsd": 0.39841269841269844,
      "change24h": 3.63714,
      "marketCap": 460077362043,
      "volume24h": 18189051573,
      "high24h": 12.58,
      "low24h": 12.11
    },
    {
      "id": "chainlink",
      "symbol": "LINK",
      "name": "Chainlink",
      "icon": "⬡",
      "price": 423.33,
      "priceUsd": 13.439047619047619,
      "change24h": 2.84427,
      "marketCap": 299437977375,
      "volume24h": 11676183327,
      "high24h": 422.76,
      "low24h": 410.82
    },
    {
      "id": "avalanche-2",
      "symbol": "AVAX",
      "name": "Avalanche",
      "icon": "🔺",
      "price": 439.43,
      "priceUsd": 13.95015873015873,
      "change24h": 2.79031,
      "marketCap": 189017181371,
      "volume24h": 11450732733,
      "high24h": 440.79,
      "low24h": 426.04
    },
    {
      "id": "polkadot",
      "symbol": "DOT",
      "name": "Polkadot",
      "icon": "●",
      "price": 68.68,
      "priceUsd": 2.1803174603174607,
      "change24h": 6.81275,
      "marketCap": 113509852572,
      "volume24h": 5423455743,
      "high24h": 68.59,
      "low24h": 64.3
    }
  ]
}