{
  "updateTime": "2026-01-29T17:40:30.754Z",
  "updateTimeLocal": "2026/1/30 上午1:40:30",
  "currency": "TWD",
  "cryptos": [
    {
      "id": "bitcoin",
      "symbol": "BTC",
      "name": "Bitcoin",
      "icon": "₿",
      "price": 2666908,
      "priceUsd": 84663.74603174604,
      "change24h": -5.14782,
      "marketCap": 53350369058120,
      "volume24h": 1956374948235,
      "high24h": 2835952,
      "low24h": 2651254
    },
    {
      "id": "ethereum",
      "symbol": "ETH",
      "name": "Ethereum",
      "icon": "Ξ",
      "price": 89192,
      "priceUsd": 2831.4920634920636,
      "change24h": -5.55067,
      "marketCap": 10778794226620,
      "volume24h": 1007841441505,
      "high24h": 94916,
      "low24h": 88033
    },
    {
      "id": "binancecoin",
      "symbol": "BNB",
      "name": "BNB",
      "icon": "🔶",
      "price": 27202,
      "priceUsd": 863.5555555555555,
      "change24h": -3.93799,
      "marketCap": 3712280038436,
      "volume24h": 70091764753,
      "high24h": 28406,
      "low24h": 26901
    },
    {
      "id": "ripple",
      "symbol": "XRP",
      "name": "XRP",
      "icon": "✕",
      "price": 57.34,
      "priceUsd": 1.8203174603174603,
      "change24h": -4.34005,
      "marketCap": 3493460631199,
      "volume24h": 128940684942,
      "high24h": 60.3,
      "low24h": 56.34
    },
    {
      "id": "solana",
      "symbol": "SOL",
      "name": "Solana",
      "icon": "◎",
      "price": 3732.73,
      "priceUsd": 118.49936507936508,
      "change24h": -5.51191,
      "marketCap": 2116018442861,
      "volume24h": 165567694771,
      "high24h": 3970.15,
      "low24h": 3667.44
    },
    {
      "id": "dogecoin",
      "symbol": "DOGE",
      "name": "Dogecoin",
      "icon": "🐕",
      "price": 3.69,
      "priceUsd": 0.11714285714285715,
      "change24h": -5.17396,
      "marketCap": 622506022514,
      "volume24h": 49072834192,
      "high24h": 3.93,
      "low24h": 3.63
    },
    {
      "id": "cardano",
      "symbol": "ADA",
      "name": "Cardano",
      "icon": "₳",
      "price": 10.57,
      "priceUsd": 0.33555555555555555,
      "change24h": -5.70809,
      "marketCap": 388995942710,
      "volume24h": 17719965928,
      "high24h": 11.29,
      "low24h": 10.39
    },
    {
      "id": "chainlink",
      "symbol": "LINK",
      "name": "Chainlink",
      "icon": "⬡",
      "price": 348,
      "priceUsd": 11.047619047619047,
      "change24h": -5.74254,
      "marketCap": 246463802327,
      "volume24h": 14232544659,
      "high24h": 372.41,
      "low24h": 343
    },
    {
      "id": "avalanche-2",
      "symbol": "AVAX",
      "name": "Avalanche",
      "icon": "🔺",
      "price": 347.8,
      "priceUsd": 11.041269841269841,
      "change24h": -7.38299,
      "marketCap": 150017544999,
      "volume24h": 13418254724,
      "high24h": 379.82,
      "low24h": 343.53
    },
    {
      "id": "polkadot",
      "symbol": "DOT",
      "name": "Polkadot",
      "icon": "●",
      "price": 54.75,
      "priceUsd": 1.7380952380952381,
      "change24h": -5.13343,
      "marketCap": 90948615275,
      "volume24h": 4156562991,
      "high24h": 58.92,
      "low24h": 54.03
    }
  ]
}