{
  "updateTime": "2026-01-15T22:26:13.925Z",
  "updateTimeLocal": "2026/1/16 上午6:26:13",
  "currency": "TWD",
  "cryptos": [
    {
      "id": "bitcoin",
      "symbol": "BTC",
      "name": "Bitcoin",
      "icon": "₿",
      "price": 3019413,
      "priceUsd": 95854.38095238095,
      "change24h": -1.68216,
      "marketCap": 60311391130758,
      "volume24h": 1923249998897,
      "high24h": 3071073,
      "low24h": 3003321
    },
    {
      "id": "ethereum",
      "symbol": "ETH",
      "name": "Ethereum",
      "icon": "Ξ",
      "price": 104302,
      "priceUsd": 3311.1746031746034,
      "change24h": -1.73559,
      "marketCap": 12591927368712,
      "volume24h": 872389175837,
      "high24h": 106750,
      "low24h": 103491
    },
    {
      "id": "binancecoin",
      "symbol": "BNB",
      "name": "BNB",
      "icon": "🔶",
      "price": 29412,
      "priceUsd": 933.7142857142857,
      "change24h": -1.57397,
      "marketCap": 4011238524881,
      "volume24h": 54145186199,
      "high24h": 29925,
      "low24h": 29188
    },
    {
      "id": "ripple",
      "symbol": "XRP",
      "name": "XRP",
      "icon": "✕",
      "price": 65.49,
      "priceUsd": 2.079047619047619,
      "change24h": -3.13209,
      "marketCap": 3975260926767,
      "volume24h": 106174793173,
      "high24h": 67.61,
      "low24h": 64.98
    },
    {
      "id": "solana",
      "symbol": "SOL",
      "name": "Solana",
      "icon": "◎",
      "price": 4490.01,
      "priceUsd": 142.54000000000002,
      "change24h": -2.996,
      "marketCap": 2537355674893,
      "volume24h": 161573011280,
      "high24h": 4628.69,
      "low24h": 4456.85
    },
    {
      "id": "dogecoin",
      "symbol": "DOGE",
      "name": "Dogecoin",
      "icon": "🐕",
      "price": 4.42,
      "priceUsd": 0.1403174603174603,
      "change24h": -4.9777,
      "marketCap": 743635079698,
      "volume24h": 48157513828,
      "high24h": 4.65,
      "low24h": 4.39
    },
    {
      "id": "cardano",
      "symbol": "ADA",
      "name": "Cardano",
      "icon": "₳",
      "price": 12.42,
      "priceUsd": 0.3942857142857143,
      "change24h": -4.87215,
      "marketCap": 456635790787,
      "volume24h": 21959449132,
      "high24h": 13.07,
      "low24h": 12.32
    },
    {
      "id": "chainlink",
      "symbol": "LINK",
      "name": "Chainlink",
      "icon": "⬡",
      "price": 432.13,
      "priceUsd": 13.718412698412699,
      "change24h": -3.33969,
      "marketCap": 305964258693,
      "volume24h": 18626020028,
      "high24h": 447.93,
      "low24h": 429
    },
    {
      "id": "avalanche-2",
      "symbol": "AVAX",
      "name": "Avalanche",
      "icon": "🔺",
      "price": 434.09,
      "priceUsd": 13.78063492063492,
      "change24h": -6.06006,
      "marketCap": 186923973118,
      "volume24h": 12682707827,
      "high24h": 462.1,
      "low24h": 431.37
    },
    {
      "id": "polkadot",
      "symbol": "DOT",
      "name": "Polkadot",
      "icon": "●",
      "price": 66.9,
      "priceUsd": 2.123809523809524,
      "change24h": -4.98847,
      "marketCap": 110702201828,
      "volume24h": 5063407877,
      "high24h": 70.51,
      "low24h": 66.37
    }
  ]
}