{
  "updateTime": "2026-01-21T18:55:57.217Z",
  "updateTimeLocal": "2026/1/22 上午2:55:57",
  "currency": "TWD",
  "cryptos": [
    {
      "id": "bitcoin",
      "symbol": "BTC",
      "name": "Bitcoin",
      "icon": "₿",
      "price": 2793760,
      "priceUsd": 88690.79365079365,
      "change24h": -1.34594,
      "marketCap": 55812966875356,
      "volume24h": 1996478261677,
      "high24h": 2853974,
      "low24h": 2760736
    },
    {
      "id": "ethereum",
      "symbol": "ETH",
      "name": "Ethereum",
      "icon": "Ξ",
      "price": 92488,
      "priceUsd": 2936.126984126984,
      "change24h": -2.23262,
      "marketCap": 11171648285422,
      "volume24h": 1065755109883,
      "high24h": 95268,
      "low24h": 90820
    },
    {
      "id": "binancecoin",
      "symbol": "BNB",
      "name": "BNB",
      "icon": "🔶",
      "price": 27600,
      "priceUsd": 876.1904761904761,
      "change24h": -2.19201,
      "marketCap": 3763250904092,
      "volume24h": 93569520958,
      "high24h": 28397,
      "low24h": 27322
    },
    {
      "id": "ripple",
      "symbol": "XRP",
      "name": "XRP",
      "icon": "✕",
      "price": 60.23,
      "priceUsd": 1.912063492063492,
      "change24h": 0.36059,
      "marketCap": 3661713168826,
      "volume24h": 138101819352,
      "high24h": 61.78,
      "low24h": 59.35
    },
    {
      "id": "solana",
      "symbol": "SOL",
      "name": "Solana",
      "icon": "◎",
      "price": 4026.31,
      "priceUsd": 127.81936507936508,
      "change24h": 0.14844,
      "marketCap": 2277621809208,
      "volume24h": 160543080393,
      "high24h": 4124.44,
      "low24h": 3974.77
    },
    {
      "id": "dogecoin",
      "symbol": "DOGE",
      "name": "Dogecoin",
      "icon": "🐕",
      "price": 3.9,
      "priceUsd": 0.1238095238095238,
      "change24h": -0.30556,
      "marketCap": 656426285985,
      "volume24h": 44534231228,
      "high24h": 4,
      "low24h": 3.83
    },
    {
      "id": "cardano",
      "symbol": "ADA",
      "name": "Cardano",
      "icon": "₳",
      "price": 11.16,
      "priceUsd": 0.3542857142857143,
      "change24h": 0.45165,
      "marketCap": 410209565469,
      "volume24h": 19177498460,
      "high24h": 11.44,
      "low24h": 11.02
    },
    {
      "id": "chainlink",
      "symbol": "LINK",
      "name": "Chainlink",
      "icon": "⬡",
      "price": 382.78,
      "priceUsd": 12.15174603174603,
      "change24h": -0.97293,
      "marketCap": 271058233831,
      "volume24h": 14623913367,
      "high24h": 394.51,
      "low24h": 378.06
    },
    {
      "id": "avalanche-2",
      "symbol": "AVAX",
      "name": "Avalanche",
      "icon": "🔺",
      "price": 382.93,
      "priceUsd": 12.156507936507937,
      "change24h": -0.12443,
      "marketCap": 165140547264,
      "volume24h": 11852733234,
      "high24h": 391.27,
      "low24h": 377.03
    },
    {
      "id": "polkadot",
      "symbol": "DOT",
      "name": "Polkadot",
      "icon": "●",
      "price": 60.44,
      "priceUsd": 1.9187301587301586,
      "change24h": 0.32897,
      "marketCap": 100149528367,
      "volume24h": 4602109610,
      "high24h": 62.32,
      "low24h": 59.5
    }
  ]
}