{
  "updateTime": "2026-02-01T07:39:27.338Z",
  "updateTimeLocal": "2026/2/1 下午3:39:27",
  "currency": "TWD",
  "cryptos": [
    {
      "id": "bitcoin",
      "symbol": "BTC",
      "name": "Bitcoin",
      "icon": "₿",
      "price": 2472978,
      "priceUsd": 78507.23809523809,
      "change24h": -6.04049,
      "marketCap": 49417846320678,
      "volume24h": 2644221295691,
      "high24h": 2636104,
      "low24h": 2435652
    },
    {
      "id": "ethereum",
      "symbol": "ETH",
      "name": "Ethereum",
      "icon": "Ξ",
      "price": 76223,
      "priceUsd": 2419.777777777778,
      "change24h": -9.90884,
      "marketCap": 9195928149011,
      "volume24h": 1546732005733,
      "high24h": 84607,
      "low24h": 74403
    },
    {
      "id": "binancecoin",
      "symbol": "BNB",
      "name": "BNB",
      "icon": "🔶",
      "price": 24524,
      "priceUsd": 778.5396825396825,
      "change24h": -8.20881,
      "marketCap": 3340668320691,
      "volume24h": 78703513645,
      "high24h": 26747,
      "low24h": 24214
    },
    {
      "id": "ripple",
      "symbol": "XRP",
      "name": "XRP",
      "icon": "✕",
      "price": 52.13,
      "priceUsd": 1.654920634920635,
      "change24h": -4.1426,
      "marketCap": 3169032993322,
      "volume24h": 208209547627,
      "high24h": 54.39,
      "low24h": 49.34
    },
    {
      "id": "solana",
      "symbol": "SOL",
      "name": "Solana",
      "icon": "◎",
      "price": 3298.21,
      "priceUsd": 104.70507936507937,
      "change24h": -11.32623,
      "marketCap": 1867533812439,
      "volume24h": 327735224947,
      "high24h": 3719.48,
      "low24h": 3180.42
    },
    {
      "id": "dogecoin",
      "symbol": "DOGE",
      "name": "Dogecoin",
      "icon": "🐕",
      "price": 3.31,
      "priceUsd": 0.10507936507936508,
      "change24h": -6.84771,
      "marketCap": 558168291464,
      "volume24h": 90359019081,
      "high24h": 3.56,
      "low24h": 3.17
    },
    {
      "id": "cardano",
      "symbol": "ADA",
      "name": "Cardano",
      "icon": "₳",
      "price": 9.3,
      "priceUsd": 0.29523809523809524,
      "change24h": -5.59017,
      "marketCap": 341649806615,
      "volume24h": 39972689805,
      "high24h": 9.86,
      "low24h": 8.86
    },
    {
      "id": "chainlink",
      "symbol": "LINK",
      "name": "Chainlink",
      "icon": "⬡",
      "price": 312.76,
      "priceUsd": 9.928888888888888,
      "change24h": -6.52784,
      "marketCap": 221259523881,
      "volume24h": 30831065819,
      "high24h": 335.07,
      "low24h": 296.72
    },
    {
      "id": "avalanche-2",
      "symbol": "AVAX",
      "name": "Avalanche",
      "icon": "🔺",
      "price": 320.95,
      "priceUsd": 10.188888888888888,
      "change24h": -4.3518,
      "marketCap": 138502440949,
      "volume24h": 22687965512,
      "high24h": 336.23,
      "low24h": 302.86
    },
    {
      "id": "polkadot",
      "symbol": "DOT",
      "name": "Polkadot",
      "icon": "●",
      "price": 48.66,
      "priceUsd": 1.5447619047619046,
      "change24h": -6.82023,
      "marketCap": 80820522936,
      "volume24h": 8692654952,
      "high24h": 52.28,
      "low24h": 46.34
    }
  ]
}