{
  "updateTime": "2025-12-18T17:26:15.109Z",
  "updateTimeLocal": "2025/12/19 上午1:26:15",
  "currency": "TWD",
  "cryptos": [
    {
      "id": "bitcoin",
      "symbol": "BTC",
      "name": "Bitcoin",
      "icon": "₿",
      "price": 2698980,
      "priceUsd": 85681.90476190476,
      "change24h": -1.49728,
      "marketCap": 54120950527727,
      "volume24h": 1579104290245,
      "high24h": 2811227,
      "low24h": 2689949
    },
    {
      "id": "ethereum",
      "symbol": "ETH",
      "name": "Ethereum",
      "icon": "Ξ",
      "price": 88458,
      "priceUsd": 2808.190476190476,
      "change24h": -2.12424,
      "marketCap": 10731935584096,
      "volume24h": 887255651530,
      "high24h": 94196,
      "low24h": 88104
    },
    {
      "id": "binancecoin",
      "symbol": "BNB",
      "name": "BNB",
      "icon": "🔶",
      "price": 25905,
      "priceUsd": 822.3809523809524,
      "change24h": -3.06741,
      "marketCap": 3581847121980,
      "volume24h": 75253926172,
      "high24h": 26810,
      "low24h": 25990
    },
    {
      "id": "ripple",
      "symbol": "XRP",
      "name": "XRP",
      "icon": "✕",
      "price": 58.31,
      "priceUsd": 1.8511111111111112,
      "change24h": -1.9897,
      "marketCap": 3545530499871,
      "volume24h": 118036351524,
      "high24h": 60.81,
      "low24h": 57.71
    },
    {
      "id": "solana",
      "symbol": "SOL",
      "name": "Solana",
      "icon": "◎",
      "price": 3840.28,
      "priceUsd": 121.9136507936508,
      "change24h": -1.44958,
      "marketCap": 2167837941814,
      "volume24h": 175407263508,
      "high24h": 4051.22,
      "low24h": 3835.18
    },
    {
      "id": "dogecoin",
      "symbol": "DOGE",
      "name": "Dogecoin",
      "icon": "🐕",
      "price": 3.87,
      "priceUsd": 0.12285714285714286,
      "change24h": -3.86207,
      "marketCap": 593839134948,
      "volume24h": 47570875104,
      "high24h": 4.11,
      "low24h": 3.9
    },
    {
      "id": "cardano",
      "symbol": "ADA",
      "name": "Cardano",
      "icon": "₳",
      "price": 11.16,
      "priceUsd": 0.3542857142857143,
      "change24h": -5.28461,
      "marketCap": 411647632016,
      "volume24h": 22228019664,
      "high24h": 11.88,
      "low24h": 11.23
    },
    {
      "id": "chainlink",
      "symbol": "LINK",
      "name": "Chainlink",
      "icon": "⬡",
      "price": 378.83,
      "priceUsd": 12.026349206349206,
      "change24h": -3.2441,
      "marketCap": 266188484390,
      "volume24h": 20228441705,
      "high24h": 403.01,
      "low24h": 381.15
    },
    {
      "id": "avalanche-2",
      "symbol": "AVAX",
      "name": "Avalanche",
      "icon": "🔺",
      "price": 362.56,
      "priceUsd": 11.509841269841269,
      "change24h": -4.27953,
      "marketCap": 156546716974,
      "volume24h": 13193899386,
      "high24h": 386.77,
      "low24h": 365.64
    },
    {
      "id": "polkadot",
      "symbol": "DOT",
      "name": "Polkadot",
      "icon": "●",
      "price": 55.88,
      "priceUsd": 1.773968253968254,
      "change24h": -3.39599,
      "marketCap": 92461749041,
      "volume24h": 6776344463,
      "high24h": 59.25,
      "low24h": 56
    }
  ]
}