{
  "updateTime": "2025-12-13T20:24:56.681Z",
  "updateTimeLocal": "2025/12/14 上午4:24:56",
  "currency": "TWD",
  "cryptos": [
    {
      "id": "bitcoin",
      "symbol": "BTC",
      "name": "Bitcoin",
      "icon": "₿",
      "price": 2824567,
      "priceUsd": 89668.79365079365,
      "change24h": 0.06811,
      "marketCap": 56382131412618,
      "volume24h": 1127566353203,
      "high24h": 2839001,
      "low24h": 2816789
    },
    {
      "id": "ethereum",
      "symbol": "ETH",
      "name": "Ethereum",
      "icon": "Ξ",
      "price": 97380,
      "priceUsd": 3091.4285714285716,
      "change24h": 1.10918,
      "marketCap": 11753386951002,
      "volume24h": 317147822425,
      "high24h": 98171,
      "low24h": 96103
    },
    {
      "id": "binancecoin",
      "symbol": "BNB",
      "name": "BNB",
      "icon": "🔶",
      "price": 28058,
      "priceUsd": 890.7301587301587,
      "change24h": 2.19073,
      "marketCap": 3863931134829,
      "volume24h": 28222001120,
      "high24h": 28322,
      "low24h": 27425
    },
    {
      "id": "ripple",
      "symbol": "XRP",
      "name": "XRP",
      "icon": "✕",
      "price": 63.32,
      "priceUsd": 2.01015873015873,
      "change24h": 1.05373,
      "marketCap": 3820330359265,
      "volume24h": 51383962048,
      "high24h": 64.03,
      "low24h": 62.62
    },
    {
      "id": "solana",
      "symbol": "SOL",
      "name": "Solana",
      "icon": "◎",
      "price": 4163.96,
      "priceUsd": 132.18920634920636,
      "change24h": 1.14261,
      "marketCap": 2339449275017,
      "volume24h": 75478802406,
      "high24h": 4204.16,
      "low24h": 4116.92
    },
    {
      "id": "dogecoin",
      "symbol": "DOGE",
      "name": "Dogecoin",
      "icon": "🐕",
      "price": 4.35,
      "priceUsd": 0.13809523809523808,
      "change24h": 2.2639,
      "marketCap": 730776344973,
      "volume24h": 16402162209,
      "high24h": 4.38,
      "low24h": 4.25
    },
    {
      "id": "cardano",
      "symbol": "ADA",
      "name": "Cardano",
      "icon": "₳",
      "price": 12.85,
      "priceUsd": 0.40793650793650793,
      "change24h": 0.1148,
      "marketCap": 471028963972,
      "volume24h": 11041677092,
      "high24h": 13.01,
      "low24h": 12.8
    },
    {
      "id": "chainlink",
      "symbol": "LINK",
      "name": "Chainlink",
      "icon": "⬡",
      "price": 430.6,
      "priceUsd": 13.669841269841271,
      "change24h": 1.18631,
      "marketCap": 300018776235,
      "volume24h": 10424638557,
      "high24h": 437.17,
      "low24h": 424.57
    },
    {
      "id": "avalanche-2",
      "symbol": "AVAX",
      "name": "Avalanche",
      "icon": "🔺",
      "price": 419.33,
      "priceUsd": 13.312063492063492,
      "change24h": 2.51343,
      "marketCap": 180117859576,
      "volume24h": 7413158700,
      "high24h": 421.43,
      "low24h": 408.66
    },
    {
      "id": "polkadot",
      "symbol": "DOT",
      "name": "Polkadot",
      "icon": "●",
      "price": 63.89,
      "priceUsd": 2.0282539682539684,
      "change24h": 2.56977,
      "marketCap": 105136845106,
      "volume24h": 3232491926,
      "high24h": 64.34,
      "low24h": 62.02
    }
  ]
}