{
  "updateTime": "2026-01-29T07:42:02.596Z",
  "updateTimeLocal": "2026/1/29 下午3:42:02",
  "currency": "TWD",
  "cryptos": [
    {
      "id": "bitcoin",
      "symbol": "BTC",
      "name": "Bitcoin",
      "icon": "₿",
      "price": 2763682,
      "priceUsd": 87735.93650793651,
      "change24h": -0.90138,
      "marketCap": 55211684176732,
      "volume24h": 1543289644947,
      "high24h": 2835952,
      "low24h": 2744992
    },
    {
      "id": "ethereum",
      "symbol": "ETH",
      "name": "Ethereum",
      "icon": "Ξ",
      "price": 92629,
      "priceUsd": 2940.6031746031745,
      "change24h": -1.45985,
      "marketCap": 11177995883199,
      "volume24h": 772093212700,
      "high24h": 95262,
      "low24h": 91934
    },
    {
      "id": "binancecoin",
      "symbol": "BNB",
      "name": "BNB",
      "icon": "🔶",
      "price": 28347,
      "priceUsd": 899.9047619047619,
      "change24h": 0.41899,
      "marketCap": 3866074841465,
      "volume24h": 42697053816,
      "high24h": 28441,
      "low24h": 27955
    },
    {
      "id": "ripple",
      "symbol": "XRP",
      "name": "XRP",
      "icon": "✕",
      "price": 59.08,
      "priceUsd": 1.8755555555555554,
      "change24h": -1.39607,
      "marketCap": 3594389863925,
      "volume24h": 81492052827,
      "high24h": 60.73,
      "low24h": 58.37
    },
    {
      "id": "solana",
      "symbol": "SOL",
      "name": "Solana",
      "icon": "◎",
      "price": 3875.64,
      "priceUsd": 123.03619047619047,
      "change24h": -2.52071,
      "marketCap": 2194353810678,
      "volume24h": 129658943514,
      "high24h": 4009.51,
      "low24h": 3834.27
    },
    {
      "id": "dogecoin",
      "symbol": "DOGE",
      "name": "Dogecoin",
      "icon": "🐕",
      "price": 3.82,
      "priceUsd": 0.12126984126984126,
      "change24h": -2.61595,
      "marketCap": 643557910891,
      "volume24h": 35902637924,
      "high24h": 3.98,
      "low24h": 3.8
    },
    {
      "id": "cardano",
      "symbol": "ADA",
      "name": "Cardano",
      "icon": "₳",
      "price": 11.01,
      "priceUsd": 0.3495238095238095,
      "change24h": -1.53757,
      "marketCap": 404830363277,
      "volume24h": 14800291200,
      "high24h": 11.41,
      "low24h": 10.89
    },
    {
      "id": "chainlink",
      "symbol": "LINK",
      "name": "Chainlink",
      "icon": "⬡",
      "price": 364.28,
      "priceUsd": 11.564444444444444,
      "change24h": -2.48748,
      "marketCap": 257955953492,
      "volume24h": 10008000639,
      "high24h": 376.91,
      "low24h": 361.72
    },
    {
      "id": "avalanche-2",
      "symbol": "AVAX",
      "name": "Avalanche",
      "icon": "🔺",
      "price": 370.12,
      "priceUsd": 11.74984126984127,
      "change24h": -2.04582,
      "marketCap": 159669868844,
      "volume24h": 8661776328,
      "high24h": 383.61,
      "low24h": 365.92
    },
    {
      "id": "polkadot",
      "symbol": "DOT",
      "name": "Polkadot",
      "icon": "●",
      "price": 56.76,
      "priceUsd": 1.801904761904762,
      "change24h": -2.25251,
      "marketCap": 94224592241,
      "volume24h": 3643527710,
      "high24h": 59.28,
      "low24h": 56.44
    }
  ]
}