{
  "updateTime": "2026-01-16T23:24:27.948Z",
  "updateTimeLocal": "2026/1/17 上午7:24:27",
  "currency": "TWD",
  "cryptos": [
    {
      "id": "bitcoin",
      "symbol": "BTC",
      "name": "Bitcoin",
      "icon": "₿",
      "price": 3019057,
      "priceUsd": 95843.07936507936,
      "change24h": -0.02084,
      "marketCap": 60293257060703,
      "volume24h": 1181255029475,
      "high24h": 3025158,
      "low24h": 2982828
    },
    {
      "id": "ethereum",
      "symbol": "ETH",
      "name": "Ethereum",
      "icon": "Ξ",
      "price": 104234,
      "priceUsd": 3309.0158730158732,
      "change24h": -0.34839,
      "marketCap": 12574664010818,
      "volume24h": 772195201526,
      "high24h": 105017,
      "low24h": 102998
    },
    {
      "id": "binancecoin",
      "symbol": "BNB",
      "name": "BNB",
      "icon": "🔶",
      "price": 29647,
      "priceUsd": 941.1746031746031,
      "change24h": 0.7149,
      "marketCap": 4040854928521,
      "volume24h": 37546321727,
      "high24h": 29659,
      "low24h": 29235
    },
    {
      "id": "ripple",
      "symbol": "XRP",
      "name": "XRP",
      "icon": "✕",
      "price": 65.43,
      "priceUsd": 2.0771428571428574,
      "change24h": -0.30549,
      "marketCap": 3978003469478,
      "volume24h": 78883594651,
      "high24h": 65.86,
      "low24h": 64.22
    },
    {
      "id": "solana",
      "symbol": "SOL",
      "name": "Solana",
      "icon": "◎",
      "price": 4583.48,
      "priceUsd": 145.50730158730158,
      "change24h": 1.95615,
      "marketCap": 2591070923958,
      "volume24h": 124828204650,
      "high24h": 4590.78,
      "low24h": 4448.32
    },
    {
      "id": "dogecoin",
      "symbol": "DOGE",
      "name": "Dogecoin",
      "icon": "🐕",
      "price": 4.37,
      "priceUsd": 0.13873015873015873,
      "change24h": -1.34311,
      "marketCap": 734929663064,
      "volume24h": 41039359426,
      "high24h": 4.43,
      "low24h": 4.29
    },
    {
      "id": "cardano",
      "symbol": "ADA",
      "name": "Cardano",
      "icon": "₳",
      "price": 12.51,
      "priceUsd": 0.39714285714285713,
      "change24h": 0.59604,
      "marketCap": 459992706707,
      "volume24h": 16930668377,
      "high24h": 12.57,
      "low24h": 12.04
    },
    {
      "id": "chainlink",
      "symbol": "LINK",
      "name": "Chainlink",
      "icon": "⬡",
      "price": 433.36,
      "priceUsd": 13.757460317460318,
      "change24h": -0.25971,
      "marketCap": 306850478777,
      "volume24h": 11396710591,
      "high24h": 437.6,
      "low24h": 426.06
    },
    {
      "id": "avalanche-2",
      "symbol": "AVAX",
      "name": "Avalanche",
      "icon": "🔺",
      "price": 430.4,
      "priceUsd": 13.663492063492063,
      "change24h": -1.26114,
      "marketCap": 185380511618,
      "volume24h": 11050035183,
      "high24h": 437.39,
      "low24h": 418.63
    },
    {
      "id": "polkadot",
      "symbol": "DOT",
      "name": "Polkadot",
      "icon": "●",
      "price": 66.97,
      "priceUsd": 2.126031746031746,
      "change24h": 0.41081,
      "marketCap": 110906445986,
      "volume24h": 4727380200,
      "high24h": 67.94,
      "low24h": 65.3
    }
  ]
}